{
    "key": "group_68d589b200f4d",
    "title": "Post Type - Event",
    "fields": [
        {
            "key": "field_68d591128d780",
            "label": "URL",
            "name": "url",
            "aria-label": "",
            "type": "url",
            "instructions": "",
            "required": 0,
            "conditional_logic": 0,
            "wrapper": {
                "width": "",
                "class": "",
                "id": ""
            },
            "default_value": "",
            "allow_in_bindings": 0,
            "placeholder": ""
        },
        {
            "key": "field_68d589b215556",
            "label": "Image",
            "name": "image",
            "aria-label": "",
            "type": "image",
            "instructions": "",
            "required": 0,
            "conditional_logic": 0,
            "wrapper": {
                "width": "",
                "class": "",
                "id": ""
            },
            "uploader": "",
            "return_format": "id",
            "library": "all",
            "upload_folder": "",
            "acfe_thumbnail": 0,
            "min_width": "",
            "min_height": "",
            "min_size": "",
            "max_width": "",
            "max_height": "",
            "max_size": "",
            "mime_types": "",
            "allow_in_bindings": 0,
            "preview_size": "medium"
        },
        {
            "key": "field_68d58ad2aebe7",
            "label": "Date or Start Date",
            "name": "date_or_start_date",
            "aria-label": "",
            "type": "date_picker",
            "instructions": "For single day events - enter the date.\r\nFor multi-day events - enter the start date.",
            "required": 0,
            "conditional_logic": 0,
            "wrapper": {
                "width": "",
                "class": "",
                "id": ""
            },
            "display_format": "F j, Y",
            "return_format": "Ymd",
            "first_day": 1,
            "default_to_current_date": 0,
            "placeholder": "",
            "min_date": "",
            "max_date": "",
            "no_weekends": 0,
            "allow_in_bindings": 0
        },
        {
            "key": "field_68d58b2caebe8",
            "label": "End Date",
            "name": "end_date",
            "aria-label": "",
            "type": "date_picker",
            "instructions": "For single day events - leave empty.\r\nFor multi-day events - enter the end date.",
            "required": 0,
            "conditional_logic": 0,
            "wrapper": {
                "width": "",
                "class": "",
                "id": ""
            },
            "display_format": "F j, Y",
            "return_format": "Ymd",
            "first_day": 1,
            "default_to_current_date": 0,
            "placeholder": "",
            "min_date": "",
            "max_date": "",
            "no_weekends": 0,
            "allow_in_bindings": 0
        },
        {
            "key": "field_68d58b6aaebe9",
            "label": "Location (Primary)",
            "name": "location_primary",
            "aria-label": "",
            "type": "textarea",
            "instructions": "",
            "required": 0,
            "conditional_logic": 0,
            "wrapper": {
                "width": "",
                "class": "",
                "id": ""
            },
            "default_value": "",
            "acfe_textarea_code": 0,
            "maxlength": "",
            "allow_in_bindings": 0,
            "rows": 4,
            "placeholder": "",
            "new_lines": "br"
        },
        {
            "key": "field_68d58b84aebea",
            "label": "Location (Secondary)",
            "name": "location_secondary",
            "aria-label": "",
            "type": "textarea",
            "instructions": "",
            "required": 0,
            "conditional_logic": 0,
            "wrapper": {
                "width": "",
                "class": "",
                "id": ""
            },
            "default_value": "",
            "acfe_textarea_code": 0,
            "maxlength": "",
            "allow_in_bindings": 0,
            "rows": 4,
            "placeholder": "",
            "new_lines": "br"
        },
        {
            "key": "field_68d58b90aebeb",
            "label": "Description",
            "name": "description",
            "aria-label": "",
            "type": "textarea",
            "instructions": "",
            "required": 0,
            "conditional_logic": 0,
            "wrapper": {
                "width": "",
                "class": "",
                "id": ""
            },
            "default_value": "",
            "acfe_textarea_code": 0,
            "maxlength": "",
            "allow_in_bindings": 0,
            "rows": 4,
            "placeholder": "",
            "new_lines": "br"
        }
    ],
    "location": [
        [
            {
                "param": "post_type",
                "operator": "==",
                "value": "event"
            }
        ]
    ],
    "menu_order": 0,
    "position": "normal",
    "style": "default",
    "label_placement": "left",
    "instruction_placement": "label",
    "hide_on_screen": [
        "the_content",
        "permalink",
        "preview",
        "slug"
    ],
    "active": true,
    "description": "",
    "show_in_rest": 0,
    "acfe_autosync": [
        "json"
    ],
    "acfe_form": 0,
    "acfe_display_title": "",
    "acfe_meta": "",
    "acfe_note": "",
    "modified": 1758850857
}
